delatore/__init__.py
delatore/__main__.py
delatore/configuration/__init__.py
delatore/configuration/dynamic.py
delatore/configuration/resources/outputs.yaml
delatore/configuration/resources/sources.yaml
delatore/configuration/static.py
delatore/outputs/__init__.py
delatore/outputs/alerta/__init__.py
delatore/outputs/alerta/alerta.py
delatore/outputs/telegram/__init__.py
delatore/outputs/telegram/bot.py
delatore/outputs/telegram/emoji.py
delatore/outputs/telegram/json2mdwn.py
delatore/outputs/telegram/messages/help.md
delatore/outputs/telegram/parsing.py
delatore/sources/__init__.py
delatore/sources/awx_api.py
delatore/sources/base.py
delatore/sources/http.py
delatore/sources/influx.py
delatore/sources/resources/error_autoscaling.txt
delatore/sources/resources/error_disk_state.txt
delatore/sources/resources/error_lb_down.txt
delatore/sources/resources/error_lb_down_fail_requests.txt
delatore/sources/resources/error_lb_timing.txt
delatore/sources/resources/error_rds_test.txt
delatore/sources/resources/error_sfs_status.txt
delatore/unified_json.py
delatore-0.5.1.dist-info/LICENSE
delatore-0.5.1.dist-info/WHEEL
delatore-0.5.1.dist-info/METADATA
delatore-0.5.1.dist-info/RECORD
