Metadata-Version: 2.1
Name: delatore
Version: 0.5.1
Summary: Bot for CSM jobs notifications in telegram and alerta
Home-page: https://github.com/opentelekomcloud-infra/delatore
License: Apache-2.0
Author: OTC customer service monitoring team
Requires-Python: >=3.7,<4.0
Classifier: License :: OSI Approved :: Apache Software License
Classifier: Programming Language :: Python :: 3
Classifier: Programming Language :: Python :: 3.7
Classifier: Programming Language :: Python :: 3.8
Classifier: Programming Language :: Python :: 3.9
Requires-Dist: aiodns (>=2.0.0,<3.0.0)
Requires-Dist: aiogram (==2.9.2)
Requires-Dist: aiohttp (>=3.6.2,<4.0.0)
Requires-Dist: aiohttp-socks (>=0.3.4,<0.4.0)
Requires-Dist: alerta (>=7.4.4,<8.0.0)
Requires-Dist: apubsub (>=0.2.5,<0.3.0)
Requires-Dist: influxdb (==5.2.3)
Requires-Dist: jinja2 (>=2.11.2,<3.0.0)
Requires-Dist: jsonschema[format] (>=3.2.0,<4.0.0)
Requires-Dist: ocomone (>=0.4.3,<0.5.0)
Requires-Dist: pyyaml-typed (>=0.1.0,<0.2.0)
Requires-Dist: rfc3339-validator (>=0.1.2,<0.2.0)
Project-URL: Repository, https://github.com/opentelekomcloud-infra/delatore
